{
  "event_id": "fixture-span-start",
  "timestamp": "2026-05-08T01:23:45.000Z",
  "observed_timestamp": "2026-05-08T01:23:45.002Z",
  "data": {
    "tenant_id": "fixture",
    "service": "codex-orchestrator",
    "event_type": "span_start",
    "signal": "span_start",
    "environment": "prod",
    "trace_id": "4bf92f3577b34da6a3ce929d0e0e4736",
    "span_id": "00f067aa0ba902b7",
    "parent_span_id": "",
    "name": "POST /v1/responses",
    "span_kind": "server",
    "start_time": "2026-05-08T01:23:45.000Z",
    "http.method": "POST",
    "http.route": "/v1/responses"
  }
}
